overflow/__init__.py
overflow-1.2.0.dist-info/LICENSE
overflow-1.2.0.dist-info/METADATA
overflow-1.2.0.dist-info/WHEEL
overflow-1.2.0.dist-info/top_level.txt
overflow-1.2.0.dist-info/RECORD
