Metadata-Version: 2.1
Name: overflow
Version: 1.2.0
Summary: from converting a list to a string to a neural network that changes the color of text based on the background color
Home-page: https://github.com/lizardwine/overflow
Author: Lizard
Author-email: lizardwine@hotmail.com
License: UNKNOWN
Project-URL: Bug Tracker, https://github.com/lizardwine/overflow/issues
Platform: UNKNOWN
Classifier: Programming Language :: Python :: 3
Classifier: License :: OSI Approved :: MIT License
Classifier: Operating System :: OS Independent
Requires-Python: >=3.6
License-File: LICENSE
